gosling/__init__.py
gosling/_version.py
gosling/_widget.py
gosling/api.py
gosling/display.py
gosling/plugin_registry.py
gosling/schemapi.py
gosling/data/__init__.py
gosling/data/_tilesets.py
gosling/examples/__init__.py
gosling/examples/area_chart.py
gosling/examples/bar_chart.py
gosling/examples/between_link_pandas.py
gosling/examples/brushing_and_linking.py
gosling/examples/circos.py
gosling/examples/comparative_matrices.py
gosling/examples/corces.py
gosling/examples/covid.py
gosling/examples/genes.py
gosling/examples/heatmap.py
gosling/examples/ideograms.py
gosling/examples/line_chart.py
gosling/examples/multiscale_lollipop_plot.py
gosling/examples/multiscale_sequence.py
gosling/examples/overview_detail.py
gosling/examples/point_plot.py
gosling/examples/text_marks.py
gosling/schema/__init__.py
gosling/schema/channels.py
gosling/schema/core.py
gosling/schema/gosling-schema.json
gosling/schema/mixins.py
gosling/sphinxext/__init__.py
gosling/sphinxext/gallery.py
gosling/sphinxext/plot.py
gosling/static/widget.js
gosling/utils/__init__.py
gosling/utils/core.py
gosling/utils/execeval.py
scripts/hatch_build.py
gosling-0.3.0.dist-info/METADATA
gosling-0.3.0.dist-info/WHEEL
gosling-0.3.0.dist-info/licenses/LICENSE
gosling-0.3.0.dist-info/RECORD
