Metadata-Version: 2.4
Name: gosling
Version: 0.3.0
Summary: Python bindings to generate Gosling visualizations
Project-URL: homepage, https://github.com/gosling-lang/gos
Author-email: Trevor Manz <trevor.j.manz@gmail.com>
License: MIT
License-File: LICENSE
Requires-Python: >=3.9
Requires-Dist: anywidget>=0.9.13
Requires-Dist: jinja2
Requires-Dist: jsonschema>=3.0
Requires-Dist: pandas
Provides-Extra: all
Requires-Dist: clodius>=0.20.1; extra == 'all'
Requires-Dist: servir>=0.2.1; extra == 'all'
